mytesthellolibrary/__init__.py
mytesthellolibrary/helloworld.py
mytesthellolibrary/mytesthellolibrary.py
mytesthellolibrary-0.4.dist-info/DESCRIPTION.rst
mytesthellolibrary-0.4.dist-info/METADATA
mytesthellolibrary-0.4.dist-info/RECORD
mytesthellolibrary-0.4.dist-info/WHEEL
mytesthellolibrary-0.4.dist-info/metadata.json
mytesthellolibrary-0.4.dist-info/top_level.txt
