Metadata-Version: 1.2
Name: mytesthellolibrary
Version: 0.4
Summary: sum two numbers
Home-page: https://github.com/sebasgverde/mytesthellolibrary
Author: Sebastian Garcia Valencia
Author-email: sebasgverde@gmail.com
License: MIT
Platform: UNKNOWN
Requires-Python: >=2.7
